py_back/__init__.py
py_back/builtins/__init__.py
py_back/builtins/_back_builtins.py
py_back/enum/__init__.py
py_back/enum/_back_enum.py
pybackport-0.3.0.post1.dist-info/licenses/LICENSE
pybackport-0.3.0.post1.dist-info/METADATA
pybackport-0.3.0.post1.dist-info/WHEEL
pybackport-0.3.0.post1.dist-info/top_level.txt
pybackport-0.3.0.post1.dist-info/RECORD
