Metadata-Version: 2.4
Name: PyBackport
Version: 0.3.0.post1
Summary: Python package to backport classes from new python releases.
Author-email: Jaime Gonzalez Gomez <jgonzg@proton.me>
License: MIT license
Project-URL: Source, https://github.com/Jtachan/PyBackport.git
Classifier: Programming Language :: Python
Classifier: Programming Language :: Python :: 3
Classifier: Programming Language :: Python :: 3.7
Classifier: Programming Language :: Python :: 3.8
Classifier: Programming Language :: Python :: 3.9
Classifier: Programming Language :: Python :: 3.10
Classifier: Programming Language :: Python :: 3.11
Classifier: Programming Language :: Python :: 3.12
Requires-Python: >=3.7
License-File: LICENSE
Dynamic: license-file
